robopython/__init__.py
robopython/ble_robo.py
robopython/matrix_characters.py
robopython/mqtt_robo.py
robopython/notes.py
robopython/robopython.py
robopython/pygatt/__init__.py
robopython/pygatt/device.py
robopython/pygatt/exceptions.py
robopython/pygatt/util.py
robopython/pygatt/backends/__init__.py
robopython/pygatt/backends/backend.py
robopython/pygatt/backends/bgapi/__init__.py
robopython/pygatt/backends/bgapi/bgapi.py
robopython/pygatt/backends/bgapi/bglib.py
robopython/pygatt/backends/bgapi/constants.py
robopython/pygatt/backends/bgapi/device.py
robopython/pygatt/backends/bgapi/error_codes.py
robopython/pygatt/backends/bgapi/exceptions.py
robopython/pygatt/backends/bgapi/packets.py
robopython/pygatt/backends/bgapi/util.py
robopython/pygatt/backends/gatttool/__init__.py
robopython/pygatt/backends/gatttool/device.py
robopython/pygatt/backends/gatttool/gatttool.py
robopython/robo/__init__.py
robopython/robo/accelerometer.py
robopython/robo/button.py
robopython/robo/camera.py
robopython/robo/colour.py
robopython/robo/display.py
robopython/robo/ir.py
robopython/robo/light.py
robopython/robo/linetracker.py
robopython/robo/matrix.py
robopython/robo/meteo.py
robopython/robo/motion.py
robopython/robo/motor.py
robopython/robo/rgb.py
robopython/robo/servo.py
robopython/robo/system.py
robopython/robo/ultrasonic.py
robopython-1.0.4.dist-info/AUTHORS.rst
robopython-1.0.4.dist-info/LICENSE
robopython-1.0.4.dist-info/METADATA
robopython-1.0.4.dist-info/WHEEL
robopython-1.0.4.dist-info/entry_points.txt
robopython-1.0.4.dist-info/top_level.txt
robopython-1.0.4.dist-info/RECORD
