Metadata-Version: 2.1
Name: robopython
Version: 1.0.4
Summary: Robo Wunderkind Python API - BLED112 USB Dongle Required
Home-page: https://github.com/JonRobo/robopython
Author: Jonathan William Morley
Author-email: jon@robowunderkind.com
License: Apache Software License 2.0
Keywords: robopython
Platform: UNKNOWN
Classifier: Development Status :: 4 - Beta
Classifier: Intended Audience :: Developers
Classifier: License :: OSI Approved :: Apache Software License
Classifier: Natural Language :: English
Classifier: Programming Language :: Python :: 2
Classifier: Programming Language :: Python :: 2.7
Classifier: Programming Language :: Python :: 3
Classifier: Programming Language :: Python :: 3.9
Requires-Dist: Click (>=6.0)
Requires-Dist: pyserial
Requires-Dist: enum-compat
Requires-Dist: pexpect
Requires-Dist: paho-mqtt
Requires-Dist: future
